medusa/__init__.py
medusa/core/__init__.py
medusa/core/ensemble.py
medusa/core/feature.py
medusa/core/member.py
medusa/flux_analysis/__init__.py
medusa/flux_analysis/deletion.py
medusa/flux_analysis/flux_balance.py
medusa/flux_analysis/variability.py
medusa/quality/__init__.py
medusa/quality/mass_balance.py
medusa/reconstruct/__init__.py
medusa/reconstruct/degrade.py
medusa/reconstruct/expand.py
medusa/reconstruct/load_from_file.py
medusa/test/__init__.py
medusa/test/test_ensemble.py
medusa/test/test_flux_balance.py
medusa/test/test_load_from_file.py
medusa/test/test_reconstruct.py
medusa/test/test_variability.py
medusa/test/data/Staphylococcus aureus.json
medusa/test/data/Staphylococcus_aureus_ensemble.pickle
medusa/test/data/Staphylococcus_aureus_repickled.pickle
medusa/test/data/biolog_base_composition.csv
medusa/test/data/plata_thresholded.csv
medusa/test/data/reactions_seed_20180809.tsv
medusa/test/data/universal_mundy.json
medusa_cobra-0.2.1.dist-info/LICENSE.txt
medusa_cobra-0.2.1.dist-info/METADATA
medusa_cobra-0.2.1.dist-info/WHEEL
medusa_cobra-0.2.1.dist-info/top_level.txt
medusa_cobra-0.2.1.dist-info/RECORD
