Metadata-Version: 2.1
Name: medusa-cobra
Version: 0.2.1
Summary: Ensemble modeling using constraint-based reconstruction and analysis (COBRA)
Home-page: https://github.com/gregmedlock/Medusa
Author: Gregory Medlock
Author-email: gmedlo@gmail.com
License: MIT
Download-URL: https://github.com/gregmedlock/Medusa/archive/0.2.1.tar.gz
Keywords: computational biology,systems biology,biology
Platform: UNKNOWN
Classifier: Development Status :: 3 - Alpha
Classifier: Intended Audience :: Science/Research
Classifier: License :: OSI Approved :: MIT License
Classifier: Programming Language :: Python :: 3
Requires-Dist: cobra (>=0.18.0)
